Workbook

Sheet Overview
A2: ITrustU risk register
A3: Initial assessment: April 1, 2020. Likelihood horizon: April 1–June 30, 2020.
A5: Assessment position | B5: Records | E5: Inherent rating | F5: Records
A6: Active risks | B6: =COUNTIF(RiskRegister!AD6:AD49,"Active") -> 41 | E6: Low | F6: =COUNTIF(RiskRegister!P6:P49,E6) -> 0
A7: Awaiting tolerability assessment | B7: =COUNTIFS(RiskRegister!AD6:AD49,"Active",RiskRegister!W6:W49,"Awaiting assessment") -> 11 | E7: Moderate | F7: =COUNTIF(RiskRegister!P6:P49,E7) -> 5
A8: Consolidated records retained | B8: =COUNTIF(RiskRegister!AD6:AD49,"Consolidated") -> 3 | E8: High | F8: =COUNTIF(RiskRegister!P6:P49,E8) -> 28
E9: Extreme | F9: =COUNTIF(RiskRegister!P6:P49,E9) -> 8
A12: FIRM area | B12: Active risks | C12: Extreme | E12: Tolerability | F12: Active risks
A13: Financial | B13: =COUNTIFS(RiskRegister!D6:D49,A13,RiskRegister!AD6:AD49,"Active") -> 12 | C13: =COUNTIFS(RiskRegister!D6:D49,A13,RiskRegister!AD6:AD49,"Active",RiskRegister!P6:P49,"Extreme") -> 2 | E13: Tolerable | F13: =COUNTIFS(RiskRegister!W6:W49,E13,RiskRegister!AD6:AD49,"Active") -> 6
A14: Infrastructure | B14: =COUNTIFS(RiskRegister!D6:D49,A14,RiskRegister!AD6:AD49,"Active") -> 13 | C14: =COUNTIFS(RiskRegister!D6:D49,A14,RiskRegister!AD6:AD49,"Active",RiskRegister!P6:P49,"Extreme") -> 3 | E14: Not tolerable | F14: =COUNTIFS(RiskRegister!W6:W49,E14,RiskRegister!AD6:AD49,"Active") -> 24
A15: Reputation | B15: =COUNTIFS(RiskRegister!D6:D49,A15,RiskRegister!AD6:AD49,"Active") -> 9 | C15: =COUNTIFS(RiskRegister!D6:D49,A15,RiskRegister!AD6:AD49,"Active",RiskRegister!P6:P49,"Extreme") -> 1 | E15: Awaiting assessment | F15: =COUNTIFS(RiskRegister!W6:W49,E15,RiskRegister!AD6:AD49,"Active") -> 11
A16: Marketing | B16: =COUNTIFS(RiskRegister!D6:D49,A16,RiskRegister!AD6:AD49,"Active") -> 7 | C16: =COUNTIFS(RiskRegister!D6:D49,A16,RiskRegister!AD6:AD49,"Active",RiskRegister!P6:P49,"Extreme") -> 2
A19: Tolerability conclusions are provisional and depend on the controls, evidence and assumptions recorded for each risk.
A21: Awaiting assessment identifies unresolved evidence needs. It does not authorize acceptance of the exposure.
A23: All 44 permanent IDs remain. Three records are consolidated into other risks and excluded from active totals. R-013 is unused.
A25: Review weekly during the initial response period and after significant incidents or changes. Escalate urgent issues immediately.

Sheet Record View
A2: Individual risk record
A3: Select a Record ID in B4. Edit the underlying entry in RiskRegister.
A4: Record ID | B4: R-001
A6: Risk Code | B6: =IFERROR(IF(INDEX(RiskRegister!$B$6:$B$49,MATCH($B$4,RiskRegister!$A$6:$A$49,0))="","",INDEX(RiskRegister!$B$6:$B$49,MATCH($B$4,RiskRegister!$A$6:$A$49,0))),"Select a valid Record ID") -> F1-E-01
A7: Risk title | B7: =IFERROR(IF(INDEX(RiskRegister!$C$6:$C$49,MATCH($B$4,RiskRegister!$A$6:$A$49,0))="","",INDEX(RiskRegister!$C$6:$C$49,MATCH($B$4,RiskRegister!$A$6:$A$49,0))),"Select a valid Record ID") -> Pandemic-response costs exceed available funds
A8: FIRM area | B8: =IFERROR(IF(INDEX(RiskRegister!$D$6:$D$49,MATCH($B$4,RiskRegister!$A$6:$A$49,0))="","",INDEX(RiskRegister!$D$6:$D$49,MATCH($B$4,RiskRegister!$A$6:$A$49,0))),"Select a valid Record ID") -> Financial
A9: Index item | B9: =IFERROR(IF(INDEX(RiskRegister!$E$6:$E$49,MATCH($B$4,RiskRegister!$A$6:$A$49,0))="","",INDEX(RiskRegister!$E$6:$E$49,MATCH($B$4,RiskRegister!$A$6:$A$49,0))),"Select a valid Record ID") -> 1.1
A10: Primary source | B10: =IFERROR(IF(INDEX(RiskRegister!$F$6:$F$49,MATCH($B$4,RiskRegister!$A$6:$A$49,0))="","",INDEX(RiskRegister!$F$6:$F$49,MATCH($B$4,RiskRegister!$A$6:$A$49,0))),"Select a valid Record ID") -> E
A11: Classification status | B11: =IFERROR(IF(INDEX(RiskRegister!$G$6:$G$49,MATCH($B$4,RiskRegister!$A$6:$A$49,0))="","",INDEX(RiskRegister!$G$6:$G$49,MATCH($B$4,RiskRegister!$A$6:$A$49,0))),"Select a valid Record ID") -> Current classification
A12: Assessment status | B12: =IFERROR(IF(INDEX(RiskRegister!$H$6:$H$49,MATCH($B$4,RiskRegister!$A$6:$A$49,0))="","",INDEX(RiskRegister!$H$6:$H$49,MATCH($B$4,RiskRegister!$A$6:$A$49,0))),"Select a valid Record ID") -> Tolerability awaiting evidence
A13: Cause or trigger | B13: =IFERROR(IF(INDEX(RiskRegister!$I$6:$I$49,MATCH($B$4,RiskRegister!$A$6:$A$49,0))="","",INDEX(RiskRegister!$I$6:$I$49,MATCH($B$4,RiskRegister!$A$6:$A$49,0))),"Select a valid Record ID") -> Urgent, unplanned spending on equipment, training, technology and continuity arrangements.
A14: Risk event | B14: =IFERROR(IF(INDEX(RiskRegister!$J$6:$J$49,MATCH($B$4,RiskRegister!$A$6:$A$49,0))="","",INDEX(RiskRegister!$J$6:$J$49,MATCH($B$4,RiskRegister!$A$6:$A$49,0))),"Select a valid Record ID") -> Required pandemic-response spending exceeds the funds available when needed.
A15: Potential impact | B15: =IFERROR(IF(INDEX(RiskRegister!$K$6:$K$49,MATCH($B$4,RiskRegister!$A$6:$A$49,0))="","",INDEX(RiskRegister!$K$6:$K$49,MATCH($B$4,RiskRegister!$A$6:$A$49,0))),"Select a valid Record ID") -> Essential improvements may be delayed or funds diverted from other commitments, weakening continuity and policyholder protection.
A16: Objective or dependency | B16: =IFERROR(IF(INDEX(RiskRegister!$L$6:$L$49,MATCH($B$4,RiskRegister!$A$6:$A$49,0))="","",INDEX(RiskRegister!$L$6:$L$49,MATCH($B$4,RiskRegister!$A$6:$A$49,0))),"Select a valid Record ID") -> Funding essential services
A17: Likelihood horizon | B17: =IFERROR(IF(INDEX(RiskRegister!$M$6:$M$49,MATCH($B$4,RiskRegister!$A$6:$A$49,0))="","",INDEX(RiskRegister!$M$6:$M$49,MATCH($B$4,RiskRegister!$A$6:$A$49,0))),"Select a valid Record ID") -> 2020-04-01 to 2020-06-30
A18: Likelihood | B18: =IFERROR(IF(INDEX(RiskRegister!$N$6:$N$49,MATCH($B$4,RiskRegister!$A$6:$A$49,0))="","",INDEX(RiskRegister!$N$6:$N$49,MATCH($B$4,RiskRegister!$A$6:$A$49,0))),"Select a valid Record ID") -> 3
A19: Magnitude | B19: =IFERROR(IF(INDEX(RiskRegister!$O$6:$O$49,MATCH($B$4,RiskRegister!$A$6:$A$49,0))="","",INDEX(RiskRegister!$O$6:$O$49,MATCH($B$4,RiskRegister!$A$6:$A$49,0))),"Select a valid Record ID") -> 4
A20: Inherent rating | B20: =IFERROR(IF(INDEX(RiskRegister!$P$6:$P$49,MATCH($B$4,RiskRegister!$A$6:$A$49,0))="","",INDEX(RiskRegister!$P$6:$P$49,MATCH($B$4,RiskRegister!$A$6:$A$49,0))),"Select a valid Record ID") -> High
A21: Likelihood reasoning | B21: =IFERROR(IF(INDEX(RiskRegister!$Q$6:$Q$49,MATCH($B$4,RiskRegister!$A$6:$A$49,0))="","",INDEX(RiskRegister!$Q$6:$Q$49,MATCH($B$4,RiskRegister!$A$6:$A$49,0))),"Select a valid Record ID") -> Urgent costs could exceed available funding, but no response budget or cash forecast establishes that a shortfall is likely.
A22: Magnitude reasoning | B22: =IFERROR(IF(INDEX(RiskRegister!$R$6:$R$49,MATCH($B$4,RiskRegister!$A$6:$A$49,0))="","",INDEX(RiskRegister!$R$6:$R$49,MATCH($B$4,RiskRegister!$A$6:$A$49,0))),"Select a valid Record ID") -> Major assumes a shortfall large enough to delay essential measures, rather than a minor budget overrun.
A23: Existing controls | B23: =IFERROR(IF(INDEX(RiskRegister!$S$6:$S$49,MATCH($B$4,RiskRegister!$A$6:$A$49,0))="","",INDEX(RiskRegister!$S$6:$S$49,MATCH($B$4,RiskRegister!$A$6:$A$49,0))),"Select a valid Record ID") -> Financial modelling of funds and expected expenditure.
A24: Control evidence status | B24: =IFERROR(IF(INDEX(RiskRegister!$T$6:$T$49,MATCH($B$4,RiskRegister!$A$6:$A$49,0))="","",INDEX(RiskRegister!$T$6:$T$49,MATCH($B$4,RiskRegister!$A$6:$A$49,0))),"Select a valid Record ID") -> Reported control; implementation and scope require verification.
A25: Control effectiveness | B25: =IFERROR(IF(INDEX(RiskRegister!$U$6:$U$49,MATCH($B$4,RiskRegister!$A$6:$A$49,0))="","",INDEX(RiskRegister!$U$6:$U$49,MATCH($B$4,RiskRegister!$A$6:$A$49,0))),"Select a valid Record ID") -> Forecasting can identify a funding shortfall but does not ensure funds are available. Financial modelling scope, pandemic costs, payment timing and available cash remain unverified.
A26: Control gap or evidence needed | B26: =IFERROR(IF(INDEX(RiskRegister!$V$6:$V$49,MATCH($B$4,RiskRegister!$A$6:$A$49,0))="","",INDEX(RiskRegister!$V$6:$V$49,MATCH($B$4,RiskRegister!$A$6:$A$49,0))),"Select a valid Record ID") -> Financial modelling scope, pandemic costs, payment timing and available cash remain unverified.
A27: Tolerability | B27: =IFERROR(IF(INDEX(RiskRegister!$W$6:$W$49,MATCH($B$4,RiskRegister!$A$6:$A$49,0))="","",INDEX(RiskRegister!$W$6:$W$49,MATCH($B$4,RiskRegister!$A$6:$A$49,0))),"Select a valid Record ID") -> Awaiting assessment
A28: Tolerability reasoning | B28: =IFERROR(IF(INDEX(RiskRegister!$X$6:$X$49,MATCH($B$4,RiskRegister!$A$6:$A$49,0))="","",INDEX(RiskRegister!$X$6:$X$49,MATCH($B$4,RiskRegister!$A$6:$A$49,0))),"Select a valid Record ID") -> The supplied information does not establish the remaining exposure after controls. Financial modelling scope, pandemic costs, payment timing and available cash remain unverified. A tolerability decision must consider the agreed appetite and the need to sustain funding essential services.
A29: Controllability | B29: =IFERROR(IF(INDEX(RiskRegister!$Y$6:$Y$49,MATCH($B$4,RiskRegister!$A$6:$A$49,0))="","",INDEX(RiskRegister!$Y$6:$Y$49,MATCH($B$4,RiskRegister!$A$6:$A$49,0))),"Select a valid Record ID") -> Controllability is partial: internal preparation and decisions can reduce exposure, while external conditions may remain beyond our control.
A30: Business imperative | B30: =IFERROR(IF(INDEX(RiskRegister!$Z$6:$Z$49,MATCH($B$4,RiskRegister!$A$6:$A$49,0))="","",INDEX(RiskRegister!$Z$6:$Z$49,MATCH($B$4,RiskRegister!$A$6:$A$49,0))),"Select a valid Record ID") -> Sustain funding essential services as part of meeting essential service and policyholder obligations. Business necessity does not itself make the exposure tolerable.
A31: Longer-term exposure | B31: =IFERROR(IF(INDEX(RiskRegister!$AA$6:$AA$49,MATCH($B$4,RiskRegister!$A$6:$A$49,0))="","",INDEX(RiskRegister!$AA$6:$AA$49,MATCH($B$4,RiskRegister!$A$6:$A$49,0))),"Select a valid Record ID") -> Consequences may extend beyond three months; reassess during weekly reviews. Initial likelihood horizon ends 2020-06-30; later information belongs to dated reviews.
A32: Risk owner | B32: =IFERROR(IF(INDEX(RiskRegister!$AB$6:$AB$49,MATCH($B$4,RiskRegister!$A$6:$A$49,0))="","",INDEX(RiskRegister!$AB$6:$AB$49,MATCH($B$4,RiskRegister!$A$6:$A$49,0))),"Select a valid Record ID") -> Finance Manager
A33: Evidence and experience | B33: =IFERROR(IF(INDEX(RiskRegister!$AC$6:$AC$49,MATCH($B$4,RiskRegister!$A$6:$A$49,0))="","",INDEX(RiskRegister!$AC$6:$AC$49,MATCH($B$4,RiskRegister!$A$6:$A$49,0))),"Select a valid Record ID") -> Business outline(1).pdf: The case confirms premium collection and investment activity, but no financial-modelling or liquidity-control specification (pp. 5–6). No internal incident history is verified. Only evidence available by 2020-04-01 can support the initial assessment.
A34: Record status | B34: =IFERROR(IF(INDEX(RiskRegister!$AD$6:$AD$49,MATCH($B$4,RiskRegister!$A$6:$A$49,0))="","",INDEX(RiskRegister!$AD$6:$AD$49,MATCH($B$4,RiskRegister!$A$6:$A$49,0))),"Select a valid Record ID") -> Active
A35: Consolidated into | B35: =IFERROR(IF(INDEX(RiskRegister!$AE$6:$AE$49,MATCH($B$4,RiskRegister!$A$6:$A$49,0))="","",INDEX(RiskRegister!$AE$6:$AE$49,MATCH($B$4,RiskRegister!$A$6:$A$49,0))),"Select a valid Record ID")
A36: Assessment as of | B36: =IFERROR(IF(INDEX(RiskRegister!$AF$6:$AF$49,MATCH($B$4,RiskRegister!$A$6:$A$49,0))="","",INDEX(RiskRegister!$AF$6:$AF$49,MATCH($B$4,RiskRegister!$A$6:$A$49,0))),"Select a valid Record ID") -> 43922
A37: Horizon end | B37: =IFERROR(IF(INDEX(RiskRegister!$AG$6:$AG$49,MATCH($B$4,RiskRegister!$A$6:$A$49,0))="","",INDEX(RiskRegister!$AG$6:$AG$49,MATCH($B$4,RiskRegister!$A$6:$A$49,0))),"Select a valid Record ID") -> 44012
A38: Owner designation | B38: =IFERROR(IF(INDEX(RiskRegister!$AH$6:$AH$49,MATCH($B$4,RiskRegister!$A$6:$A$49,0))="","",INDEX(RiskRegister!$AH$6:$AH$49,MATCH($B$4,RiskRegister!$A$6:$A$49,0))),"Select a valid Record ID") -> Proposed accountable role; individual to be designated

Sheet RiskRegister
A2: ITrustU risk register
A3: Initial assessment: April 1, 2020. Likelihood horizon ends June 30, 2020. Inherent ratings and tolerability are assessed separately.
A5: Record ID | B5: Risk Code | C5: Risk title | D5: FIRM area | E5: Index item | F5: Primary source | G5: Classification status | H5: Assessment status | I5: Cause or trigger | J5: Risk event | K5: Potential impact | L5: Objective or dependency | M5: Likelihood horizon | N5: Likelihood | O5: Magnitude | P5: Inherent rating | Q5: Likelihood reasoning | R5: Magnitude reasoning | S5: Existing controls | T5: Control evidence status | U5: Control effectiveness | V5: Control gap or evidence needed | W5: Tolerability | X5: Tolerability reasoning | Y5: Controllability | Z5: Business imperative | AA5: Longer-term exposure | AB5: Risk owner | AC5: Evidence and experience | AD5: Record status | AE5: Consolidated into | AF5: Assessment as of | AG5: Horizon end | AH5: Owner designation
A6: R-001 | B6: F1-E-01 | C6: Pandemic-response costs exceed available funds | D6: Financial | E6: 1.1 | F6: E | G6: Current classification | H6: Tolerability awaiting evidence | I6: Urgent, unplanned spending on equipment, training, technology and continuity arrangements. | J6: Required pandemic-response spending exceeds the funds available when needed. | K6: Essential improvements may be delayed or funds diverted from other commitments, weakening continuity and policyholder protection. | L6: Funding essential services | M6: 2020-04-01 to 2020-06-30 | N6: 3 | O6: 4 | P6: =IF(AD6="Consolidated","Consolidated",IF(OR(N6="",O6=""),"Not assessed",INDEX('Assessment Guide'!$B$5:$F$9,N6,O6))) -> High | Q6: Urgent costs could exceed available funding, but no response budget or cash forecast establishes that a shortfall is likely. | R6: Major assumes a shortfall large enough to delay essential measures, rather than a minor budget overrun. | S6: Financial modelling of funds and expected expenditure. | T6: Reported control; implementation and scope require verification. | U6: Forecasting can identify a funding shortfall but does not ensure funds are available. Financial modelling scope, pandemic costs, payment timing and available cash remain unverified. | V6: Financial modelling scope, pandemic costs, payment timing and available cash remain unverified. | W6: Awaiting assessment | X6: The supplied information does not establish the remaining exposure after controls. Financial modelling scope, pandemic costs, payment timing and available cash remain unverified. A tolerability decision must consider the agreed appetite and the need to sustain funding essential services. | Y6: Controllability is partial: internal preparation and decisions can reduce exposure, while external conditions may remain beyond our control. | Z6: Sustain funding essential services as part of meeting essential service and policyholder obligations. Business necessity does not itself make the exposure tolerable. | AA6: Consequences may extend beyond three months; reassess during weekly reviews. Initial likelihood horizon ends 2020-06-30; later information belongs to dated reviews. | AB6: Finance Manager | AC6: Business outline(1).pdf: The case confirms premium collection and investment activity, but no financial-modelling or liquidity-control specification (pp. 5–6). No internal incident history is verified. Only evidence available by 2020-04-01 can support the initial assessment. | AD6: Active | AF6: 43922 | AG6: 44012 | AH6: Proposed accountable role; individual to be designated
A7: R-002 | B7: F1-S-01 | C7: Tiva financial support is unavailable or unsuitable | D7: Financial | E7: 1.1 | F7: S | G7: Current classification | H7: Tolerability awaiting evidence | I7: Competing demands across the group and unconfirmed support terms. | J7: Financial support sought from Tiva is unavailable, delayed or offered on unsuitable terms. | K7: Alternative funding may be required or essential pandemic expenditure delayed. | L7: Independent financial capacity | M7: 2020-04-01 to 2020-06-30 | N7: 3 | O7: 4 | P7: =IF(AD7="Consolidated","Consolidated",IF(OR(N7="",O7=""),"Not assessed",INDEX('Assessment Guide'!$B$5:$F$9,N7,O7))) -> High | Q7: Competing group demands make delay plausible. Unconfirmed support alone does not establish its probability of being unavailable. | R7: Major is conditional on essential expenditure needing Tiva support and insufficient alternatives. Dependence has not been established. | S7: Financial modelling may assess funding needs and independent financial capacity; a scenario without Tiva support is unverified. | T7: Reported control; implementation and scope require verification. | U7: Forecasting can identify a funding shortfall but does not ensure funds are available. Requested funding, independent funding capacity, support terms and alternatives need confirmation. | V7: Requested funding, independent funding capacity, support terms and alternatives need confirmation. | W7: Awaiting assessment | X7: The supplied information does not establish the remaining exposure after controls. Requested funding, independent funding capacity, support terms and alternatives need confirmation. A tolerability decision must consider the agreed appetite and the need to sustain independent financial capacity. | Y7: Controllability is partial: internal preparation and decisions can reduce exposure, while external conditions may remain beyond our control. | Z7: Sustain independent financial capacity as part of meeting essential service and policyholder obligations. Business necessity does not itself make the exposure tolerable. | AA7: Consequences may extend beyond three months; reassess during weekly reviews. Initial likelihood horizon ends 2020-06-30; later information belongs to dated reviews. | AB7: Finance Manager | AC7: Business outline(1).pdf: The case confirms premium collection and investment activity, but no financial-modelling or liquidity-control specification (pp. 5–6). No internal incident history is verified. Only evidence available by 2020-04-01 can support the initial assessment. | AD7: Active | AF7: 43922 | AG7: 44012 | AH7: Proposed accountable role; individual to be designated
A8: R-003 | B8: F2-G-01 | C8: Resources are allocated away from significant risks | D8: Financial | E8: 1.2 | F8: G | G8: Current classification | H8: Initial assessment; conclusions provisional | I8: Allocation decisions do not consistently consider exposure, urgency and dependencies. | J8: Funding and specialist capacity are directed away from essential risk priorities. | K8: Critical controls may remain under-resourced while less urgent work consumes capacity, increasing service and financial exposure. | L8: Resource allocation across essential functions | M8: 2020-04-01 to 2020-06-30 | N8: 3 | O8: 4 | P8: =IF(AD8="Consolidated","Consolidated",IF(OR(N8="",O8=""),"Not assessed",INDEX('Assessment Guide'!$B$5:$F$9,N8,O8))) -> High | Q8: Rapidly changing demands create a plausible allocation mismatch; the index alone does not prove current misallocation. | R8: A material mismatch could leave essential continuity measures unfunded and threaten obligations. | S8: Assessment assumption: financial modelling is in use for funds and expenditure. The case confirms financial activities, not this control. | T8: Mixed evidence: case arrangements plus explicit assessment assumptions; see Evidence and experience. | U8: Modelling can identify pressure but does not provide cash, prevent losses or prove scenario coverage. Effectiveness is unverified. | V8: Evidence that budgets follow agreed priorities and delegated authority is missing. | W8: Not tolerable | X8: Not tolerable on the working assumption that allocation and oversight gaps leave essential priorities under-resourced. Continuing operations requires coordinated allocation, not acceptance of unmanaged misallocation. | Y8: Controllability is substantial for the identified internal cause, subject to available resources and verified implementation. | Z8: Sustain resource allocation across essential functions as part of meeting essential service and policyholder obligations. Business necessity does not itself make the exposure tolerable. | AA8: Consequences may extend beyond three months; reassess during weekly reviews. Initial likelihood horizon ends 2020-06-30; later information belongs to dated reviews. | AB8: Finance Manager | AC8: Business outline(1).pdf: The case confirms premium collection and investment activity, but no financial-modelling or liquidity-control specification (pp. 5–6). No internal incident history is verified. Only evidence available by 2020-04-01 can support the initial assessment. | AD8: Active | AF8: 43922 | AG8: 44012 | AH8: Proposed accountable role; individual to be designated
A9: R-004 | B9: F2-E-01 | C9: Urgent claims require investment sales at a loss | D9: Financial | E9: 1.2 | F9: E | G9: Current classification | H9: Tolerability awaiting evidence | I9: Claims payments accelerate while asset prices fall and liquid funds are constrained. | J9: Investments must be sold at unfavourable prices to meet immediate cash needs. | K9: Realized losses reduce financial capacity and future returns, potentially weakening claims funding. | L9: Claims liquidity | M9: 2020-04-01 to 2020-06-30 | N9: 3 | O9: 4 | P9: =IF(AD9="Consolidated","Consolidated",IF(OR(N9="",O9=""),"Not assessed",INDEX('Assessment Guide'!$B$5:$F$9,N9,O9))) -> High | Q9: Simultaneous claims and market pressure make forced sales plausible, but cash-flow and asset maturity evidence is absent. | R9: Major assumes forced sales materially weaken financial capacity; modest planned sales would have less impact. | S9: Assessment assumption: financial modelling is in use for funds and expenditure. The case confirms financial activities, not this control. | T9: Mixed evidence: case arrangements plus explicit assessment assumptions; see Evidence and experience. | U9: Modelling can identify pressure but does not provide cash, prevent losses or prove scenario coverage. Effectiveness is unverified. | V9: Cash forecasts, asset liquidity, planned sales and alternative funding need confirmation. | W9: Awaiting assessment | X9: Awaiting assessment: the case does not quantify the exposure and available financial capacity sufficiently to decide whether the remaining risk fits appetite. Cash forecasts, asset liquidity, planned sales and alternative funding need confirmation. Continued operations require this assessment; a High or Extreme inherent rating alone is not a tolerability decision. | Y9: Controllability is partial: internal preparation and decisions can reduce exposure, while external conditions may remain beyond our control. | Z9: Sustain claims liquidity as part of meeting essential service and policyholder obligations. Business necessity does not itself make the exposure tolerable. | AA9: Consequences may extend beyond three months; reassess during weekly reviews. Initial likelihood horizon ends 2020-06-30; later information belongs to dated reviews. | AB9: Finance Manager | AC9: Business outline(1).pdf: The case confirms premium collection and investment activity, but no financial-modelling or liquidity-control specification (pp. 5–6). No internal incident history is verified. Only evidence available by 2020-04-01 can support the initial assessment. | AD9: Active | AF9: 43922 | AG9: 44012 | AH9: Proposed accountable role; individual to be designated
A10: R-005 | B10: F3-C-01 | C10: Fraudulent claims obtain unauthorized payouts | D10: Financial | E10: 1.3 | F10: C | G10: Current classification | H10: Initial assessment; conclusions provisional | I10: Deliberate deception, fabricated evidence or account manipulation exploits verification weaknesses. | J10: Fraudulent claims are accepted and paid. | K10: Financial losses, investigation costs and customer mistrust may result; compromised accounts could also expose information. | L10: Accurate claims payments and customer information | M10: 2020-04-01 to 2020-06-30 | N10: 3 | O10: 4 | P10: =IF(AD10="Consolidated","Consolidated",IF(OR(N10="",O10=""),"Not assessed",INDEX('Assessment Guide'!$B$5:$F$9,N10,O10))) -> High | Q10: Remote processing and verification pressure could enable fraud; no reliable frequency data supports a higher likelihood. | R10: Organized or repeated fraud could create substantial losses; isolated low-value fraud would be less severe. | S10: Case: record keeping and database administration. Assessment assumption: an operational audit trail is maintained. | T10: Mixed evidence: case arrangements plus explicit assessment assumptions; see Evidence and experience. | U10: Records support detection and investigation. They do not demonstrate preventive approval, fraud detection or counterparty protection. | V10: Payout authorization, segregation of duties and fraud detection are not evidenced in the submissions. | W10: Not tolerable | X10: Not tolerable on the assumption that material verification and payout-approval weaknesses persist. Basic records alone do not support accepting avoidable material fraud while claims payments continue. | Y10: Controllability is substantial for the identified internal cause, subject to available resources and verified implementation. | Z10: Sustain accurate claims payments and customer information as part of meeting essential service and policyholder obligations. Business necessity does not itself make the exposure tolerable. | AA10: Consequences may extend beyond three months; reassess during weekly reviews. Initial likelihood horizon ends 2020-06-30; later information belongs to dated reviews. | AB10: Claims Manager | AC10: Business outline(1).pdf: The case confirms record keeping and database administration (p. 6), but not an effective transaction audit trail or approval process. No internal incident history is verified. Only evidence available by 2020-04-01 can support the initial assessment. | AD10: Active | AF10: 43922 | AG10: 44012 | AH10: Proposed accountable role; individual to be designated
A11: R-006 | B11: F3-S-01 | C11: Outsourced control activities fail | D11: Financial | E11: 1.3 | F11: S | G11: Current classification | H11: Initial assessment; conclusions provisional | I11: Critical control work depends on providers whose own capacity may deteriorate. | J11: An outsourced control is not performed reliably or fails to detect a material issue. | K11: Errors, unauthorized transactions or security issues may persist, causing financial loss and reputational harm. | L11: Reliable third-party controls | M11: 2020-04-01 to 2020-06-30 | N11: 3 | O11: 4 | P11: =IF(AD11="Consolidated","Consolidated",IF(OR(N11="",O11=""),"Not assessed",INDEX('Assessment Guide'!$B$5:$F$9,N11,O11))) -> High | Q11: Provider pressure makes failure plausible; outsourcing itself does not establish control failure. | R11: Major assumes failure of a critical control with material financial or information consequences. | S11: Case: record keeping and database administration. Assessment assumption: an operational audit trail is maintained. | T11: Mixed evidence: case arrangements plus explicit assessment assumptions; see Evidence and experience. | U11: Records support detection and investigation. They do not demonstrate preventive approval, fraud detection or counterparty protection. | V11: Control responsibilities, supplier assurance and operating evidence need verification. | W11: Not tolerable | X11: Not tolerable on the assumption that critical outsourced controls lack effective oversight. Provider involvement does not remove ITrustU’s accountability for material failures. | Y11: Controllability is partial: internal preparation and decisions can reduce exposure, while external conditions may remain beyond our control. | Z11: Sustain reliable third-party controls as part of meeting essential service and policyholder obligations. Business necessity does not itself make the exposure tolerable. | AA11: Consequences may extend beyond three months; reassess during weekly reviews. Initial likelihood horizon ends 2020-06-30; later information belongs to dated reviews. | AB11: Finance Manager | AC11: Business outline(1).pdf: The case confirms record keeping and database administration (p. 6), but not an effective transaction audit trail or approval process. No internal incident history is verified. Only evidence available by 2020-04-01 can support the initial assessment. | AD11: Active | AF11: 43922 | AG11: 44012 | AH11: Proposed accountable role; individual to be designated
A12: R-007 | B12: F3-S-02 | C12: Bank partners delay premium remittance | D12: Financial | E12: 1.3 | F12: S | G12: Current classification | H12: Tolerability awaiting evidence | I12: Payment-processing disruption or counterparty difficulties interrupt remittance. | J12: Premiums collected through bank partners do not reach ITrustU when due. | K12: Cash inflows may fall short of planned claims and operating payments; reconciliation work and customer enquiries increase. | L12: Premium cash inflow | M12: 2020-04-01 to 2020-06-30 | N12: 2 | O12: 4 | P12: =IF(AD12="Consolidated","Consolidated",IF(OR(N12="",O12=""),"Not assessed",INDEX('Assessment Guide'!$B$5:$F$9,N12,O12))) -> High | Q12: Disruption is conceivable but no bank-specific weakness establishes it as likely during three months. | R12: Major assumes a material or prolonged remittance interruption rather than a brief settlement delay. | S12: Case: record keeping and database administration. Assessment assumption: an operational audit trail is maintained. | T12: Mixed evidence: case arrangements plus explicit assessment assumptions; see Evidence and experience. | U12: Records support detection and investigation. They do not demonstrate preventive approval, fraud detection or counterparty protection. | V12: Bank arrangements, reconciliations, concentration and liquidity buffers are unverified. | W12: Awaiting assessment | X12: Awaiting assessment: the case does not quantify the exposure and available financial capacity sufficiently to decide whether the remaining risk fits appetite. Bank arrangements, reconciliations, concentration and liquidity buffers are unverified. Continued operations require this assessment; a High or Extreme inherent rating alone is not a tolerability decision. | Y12: Controllability is partial: internal preparation and decisions can reduce exposure, while external conditions may remain beyond our control. | Z12: Sustain premium cash inflow as part of meeting essential service and policyholder obligations. Business necessity does not itself make the exposure tolerable. | AA12: Consequences may extend beyond three months; reassess during weekly reviews. Initial likelihood horizon ends 2020-06-30; later information belongs to dated reviews. | AB12: Finance Manager | AC12: Business outline(1).pdf: The case confirms record keeping and database administration (p. 6), but not an effective transaction audit trail or approval process. No internal incident history is verified. Only evidence available by 2020-04-01 can support the initial assessment. | AD12: Active | AF12: 43922 | AG12: 44012 | AH12: Proposed accountable role; individual to be designated
A13: R-008 | B13: F3-S-03 | C13: Reinsurance recoveries are delayed or unpaid | D13: Financial | E13: 1.3 | F13: S | G13: Current classification | H13: Tolerability awaiting evidence | I13: Reinsurer financial pressure, disputed coverage or processing disruption. | J13: Contractually expected reinsurance recoveries are not received when needed. | K13: ITrustU must fund claims for longer or absorb unrecovered amounts, potentially threatening financial viability. | L13: Claims funding and reinsurance counterparties | M13: 2020-04-01 to 2020-06-30 | N13: 2 | O13: 4 | P13: =IF(AD13="Consolidated","Consolidated",IF(OR(N13="",O13=""),"Not assessed",INDEX('Assessment Guide'!$B$5:$F$9,N13,O13))) -> High | Q13: No counterparty-specific evidence establishes likely failure; exposure depends on actual contracts and recoveries due. | R13: Major: a material delayed or unpaid recovery requires significant funding adjustments and threatens timely claims settlement. Severe escalation requires recoveries large enough to threaten sustained claims-paying capacity or viability; amounts and arrangements are unknown. | S13: Assessment assumption: financial modelling is in use for funds and expenditure. The case confirms financial activities, not this control. | T13: Mixed evidence: case arrangements plus explicit assessment assumptions; see Evidence and experience. | U13: Modelling can identify pressure but does not provide cash, prevent losses or prove scenario coverage. Effectiveness is unverified. | V13: Coverage, exclusions, counterparties, recoveries due and ability to bridge delays are unknown. | W13: Awaiting assessment | X13: Awaiting assessment: the case does not quantify the exposure and available financial capacity sufficiently to decide whether the remaining risk fits appetite. Coverage, exclusions, counterparties, recoveries due and ability to bridge delays are unknown. Continued operations require this assessment; a High or Extreme inherent rating alone is not a tolerability decision. | Y13: Controllability is partial: internal preparation and decisions can reduce exposure, while external conditions may remain beyond our control. | Z13: Sustain claims funding and reinsurance counterparties as part of meeting essential service and policyholder obligations. Business necessity does not itself make the exposure tolerable. | AA13: Consequences may extend beyond three months; reassess during weekly reviews. Initial likelihood horizon ends 2020-06-30; later information belongs to dated reviews. | AB13: Finance Manager | AC13: Business outline(1).pdf: The case confirms premium collection and investment activity, but no financial-modelling or liquidity-control specification (pp. 5–6). No internal incident history is verified. Only evidence available by 2020-04-01 can support the initial assessment. | AD13: Active | AF13: 43922 | AG13: 44012 | AH13: Proposed accountable role; individual to be designated
A14: R-009 | B14: F3-E-01 | C14: Bond issuers default on obligations | D14: Financial | E14: 1.3 | F14: E | G14: Current classification | H14: Tolerability awaiting evidence | I14: Economic stress weakens issuers held in the investment portfolio. | J14: An issuer fails to pay interest or principal when due. | K14: Investment losses and reduced cash inflows weaken funds available for operations and policyholder obligations. | L14: Investment cash flows | M14: 2020-04-01 to 2020-06-30 | N14: 2 | O14: 4 | P14: =IF(AD14="Consolidated","Consolidated",IF(OR(N14="",O14=""),"Not assessed",INDEX('Assessment Guide'!$B$5:$F$9,N14,O14))) -> High | Q14: A stressed economy raises concern, but portfolio quality and issuer exposure are unavailable. | R14: Major assumes material concentration or multiple defaults; a small diversified holding may have less impact. | S14: Assessment assumption: financial modelling is in use for funds and expenditure. The case confirms financial activities, not this control. | T14: Mixed evidence: case arrangements plus explicit assessment assumptions; see Evidence and experience. | U14: Modelling can identify pressure but does not provide cash, prevent losses or prove scenario coverage. Effectiveness is unverified. | V14: Portfolio holdings, credit quality, concentration and credit monitoring need confirmation. | W14: Awaiting assessment | X14: Awaiting assessment: the case does not quantify the exposure and available financial capacity sufficiently to decide whether the remaining risk fits appetite. Portfolio holdings, credit quality, concentration and credit monitoring need confirmation. Continued operations require this assessment; a High or Extreme inherent rating alone is not a tolerability decision. | Y14: Controllability is partial: internal preparation and decisions can reduce exposure, while external conditions may remain beyond our control. | Z14: Sustain investment cash flows as part of meeting essential service and policyholder obligations. Business necessity does not itself make the exposure tolerable. | AA14: Consequences may extend beyond three months; reassess during weekly reviews. Initial likelihood horizon ends 2020-06-30; later information belongs to dated reviews. | AB14: Finance Manager | AC14: Business outline(1).pdf: The case confirms premium collection and investment activity, but no financial-modelling or liquidity-control specification (pp. 5–6). No internal incident history is verified. Only evidence available by 2020-04-01 can support the initial assessment. | AD14: Active | AF14: 43922 | AG14: 44012 | AH14: Proposed accountable role; individual to be designated
A15: R-010 | B15: F4-E-01 | C15: Weather-related claims pressure claims-paying capacity | D15: Financial | E15: 1.4 | F15: E | G15: Current classification | H15: Tolerability awaiting evidence | I15: A major weather event affects many insured customers during the pandemic. | J15: A major weather event generates concentrated claims that place substantial pressure on claims-paying capacity. | K15: A sudden demand for claims payments may require significant funding adjustments and delay settlement, harming customers and confidence. Financial exhaustion is not assumed in the base scenario. | L15: Claims-paying capacity | M15: 2020-04-01 to 2020-06-30 | N15: 2 | O15: 4 | P15: =IF(AD15="Consolidated","Consolidated",IF(OR(N15="",O15=""),"Not assessed",INDEX('Assessment Guide'!$B$5:$F$9,N15,O15))) -> High | Q15: A catastrophe is possible but not established as likely in the initial three-month period. | R15: Major: Ontario concentration supports a credible substantial claims shock. Severe escalation would require losses overwhelming available resources and protection, which the case does not quantify. | S15: Assessment assumption: financial modelling is in use for funds and expenditure. The case confirms financial activities, not this control. | T15: Mixed evidence: case arrangements plus explicit assessment assumptions; see Evidence and experience. | U15: Modelling can identify pressure but does not provide cash, prevent losses or prove scenario coverage. Effectiveness is unverified. | V15: Catastrophe exposure, reserves, liquid assets and reinsurance protection are unverified. | W15: Awaiting assessment | X15: Awaiting assessment: the case does not quantify the exposure and available financial capacity sufficiently to decide whether the remaining risk fits appetite. Catastrophe exposure, reserves, liquid assets and reinsurance protection are unverified. Continued operations require this assessment; a High or Extreme inherent rating alone is not a tolerability decision. | Y15: Controllability is partial: internal preparation and decisions can reduce exposure, while external conditions may remain beyond our control. | Z15: Sustain claims-paying capacity as part of meeting essential service and policyholder obligations. Business necessity does not itself make the exposure tolerable. | AA15: Retain catastrophe exposure beyond the initial horizon; re-evaluate likelihood for each subsequent period. Initial likelihood horizon ends 2020-06-30; later information belongs to dated reviews. | AB15: Finance Manager | AC15: Business outline(1).pdf: The case confirms premium collection and investment activity, but no financial-modelling or liquidity-control specification (pp. 5–6). No internal incident history is verified. Only evidence available by 2020-04-01 can support the initial assessment. | AD15: Active | AF15: 43922 | AG15: 44012 | AH15: Proposed accountable role; individual to be designated
A16: R-011 | B16: F4-E-02 | C16: Concurrent covered claims strain payment capacity | D16: Financial | E16: 1.4 | F16: E | G16: Current classification | H16: Tolerability awaiting evidence | I16: Pandemic disruption increases covered claims across relevant product lines within a short period. | J16: Concurrent payable claims exceed planned payment and handling capacity. | K16: Liquidity pressure and claims delays may threaten policyholder obligations and customer trust. | L16: Claims funding and staffing | M16: 2020-04-01 to 2020-06-30 | N16: 4 | O16: 4 | P16: =IF(AD16="Consolidated","Consolidated",IF(OR(N16="",O16=""),"Not assessed",INDEX('Assessment Guide'!$B$5:$F$9,N16,O16))) -> Extreme | Q16: Likely provisional judgment: disruption may concentrate covered claims, particularly relevant cancellations. Product terms, exclusions and submitted versus payable amounts must be distinguished. No separate medical product or automatic pandemic cover is assumed. | R16: Major assumes a substantial covered-claims concentration. Enquiries and exclusions do not automatically become payable claims. | S16: Assessment assumption: financial modelling is in use for funds and expenditure. The case confirms financial activities, not this control. | T16: Mixed evidence: case arrangements plus explicit assessment assumptions; see Evidence and experience. | U16: Modelling can identify pressure but does not provide cash, prevent losses or prove scenario coverage. Effectiveness is unverified. | V16: Product coverage, claim volumes, forecasts and reserve adequacy need confirmation. | W16: Awaiting assessment | X16: Awaiting assessment: the case does not quantify the exposure and available financial capacity sufficiently to decide whether the remaining risk fits appetite. Product coverage, claim volumes, forecasts and reserve adequacy need confirmation. Continued operations require this assessment; a High or Extreme inherent rating alone is not a tolerability decision. | Y16: Controllability is partial: internal preparation and decisions can reduce exposure, while external conditions may remain beyond our control. | Z16: Sustain claims funding and staffing as part of meeting essential service and policyholder obligations. Business necessity does not itself make the exposure tolerable. | AA16: Consequences may extend beyond three months; reassess during weekly reviews. Initial likelihood horizon ends 2020-06-30; later information belongs to dated reviews. | AB16: Finance Manager | AC16: Business outline(1).pdf: The case confirms premium collection and investment activity, but no financial-modelling or liquidity-control specification (pp. 5–6). No internal incident history is verified. Only evidence available by 2020-04-01 can support the initial assessment. | AD16: Active | AF16: 43922 | AG16: 44012 | AH16: Proposed accountable role; individual to be designated
A17: R-012 | B17: F4-E-03 | C17: Falling yields weaken funding of long-term obligations | D17: Financial | E17: 1.4 | F17: E | G17: Current classification | H17: Tolerability awaiting evidence | I17: Lower market yields reduce reinvestment returns and may increase the value of long-duration liabilities. | J17: Income and assets available to support life and pension obligations become less adequate relative to those obligations. | K17: Financial margins and funding capacity may deteriorate, with effects extending well beyond three months. | L17: Long-term policyholder funding | M17: 2020-04-01 to 2020-06-30 | N17: 4 | O17: 4 | P17: =IF(AD17="Consolidated","Consolidated",IF(OR(N17="",O17=""),"Not assessed",INDEX('Assessment Guide'!$B$5:$F$9,N17,O17))) -> Extreme | Q17: A pandemic-related rate decline is plausible and likely, but the exact scenario date and portfolio sensitivity remain unspecified. | R17: Major depends on duration mismatch and exposure size; the effect is not an automatic immediate cash shortfall. | S17: Assessment assumption: financial modelling is in use for funds and expenditure. The case confirms financial activities, not this control. | T17: Mixed evidence: case arrangements plus explicit assessment assumptions; see Evidence and experience. | U17: Modelling can identify pressure but does not provide cash, prevent losses or prove scenario coverage. Effectiveness is unverified. | V17: Asset-liability modelling, duration sensitivity and stress scenarios need verification. | W17: Awaiting assessment | X17: Awaiting assessment: the case does not quantify the exposure and available financial capacity sufficiently to decide whether the remaining risk fits appetite. Asset-liability modelling, duration sensitivity and stress scenarios need verification. Continued operations require this assessment; a High or Extreme inherent rating alone is not a tolerability decision. | Y17: Controllability is partial: internal preparation and decisions can reduce exposure, while external conditions may remain beyond our control. | Z17: Sustain long-term policyholder funding as part of meeting essential service and policyholder obligations. Business necessity does not itself make the exposure tolerable. | AA17: Long-duration funding effects may build beyond three months. Review longer-term sensitivity separately; do not interpret the three-month likelihood as lifetime exposure. Initial likelihood horizon ends 2020-06-30; later information belongs to dated reviews. | AB17: Finance Manager | AC17: Business outline(1).pdf: The case confirms premium collection and investment activity, but no financial-modelling or liquidity-control specification (pp. 5–6). No internal incident history is verified. Only evidence available by 2020-04-01 can support the initial assessment. | AD17: Active | AF17: 43922 | AG17: 44012 | AH17: Proposed accountable role; individual to be designated
... A27: R-023 | B27: I3-P-01 | C27: Limited monitoring capacity delays incident detection | D27: Infrastructure | E27: 2.3 | F27: P | G27: Current classification | H27: Initial assessment; conclusions provisional | I27: IT staffing or coverage does not match monitoring needs. | J27: A significant incident remains undetected or unattended outside available coverage. | K27: An outage or compromise persists longer, increasing recovery costs and customer harm. | L27: IT staffing and detection | M27: 2020-04-01 to 2020-06-30 | N27: 3 | O27: 4 | P27: =IF(AD27="Consolidated","Consolidated",IF(OR(N27="",O27=""),"Not assessed",INDEX('Assessment Guide'!$B$5:$F$9,N27,O27))) -> High | Q27: Six staff alone does not prove a coverage gap; schedules and external monitoring determine exposure. | R27: Major assumes delayed detection of a significant incident rather than every after-hours alert. | S27: No staff-continuity or wellbeing control is specified in the case. Assessment assumption: assumed preparation gaps apply at the assessment date. | T27: Mixed evidence: case arrangements plus explicit assessment assumptions; see Evidence and experience. | U27: Existing staffing is capacity, not a tested continuity control. Backup coverage and support effectiveness remain unverified. | V27: Staff schedules, vendor monitoring and alert escalation coverage are unknown. | W27: Not tolerable | X27: Not tolerable if a material incident can remain unattended because monitoring coverage is inadequate. Staffing numbers alone do not establish this gap; the decision is conditional on the stated coverage assumption. | Y27: Controllability is substantial for the identified internal cause, subject to available resources and verified implementation. | Z27: Sustain it staffing and detection as part of meeting essential service and policyholder obligations. Business necessity does not itself make the exposure tolerable. | AA27: Consequences may extend beyond three months; reassess during weekly reviews. Initial likelihood horizon ends 2020-06-30; later information belongs to dated reviews. | AB27: Network Manager | AC27: Business outline(1).pdf: The case confirms a small workforce and functional roles (pp. 6–7), but no trained backup or staff-continuity arrangements. No internal incident history is verified. Only evidence available by 2020-04-01 can support the initial assessment. | AD27: Active | AF27: 43922 | AG27: 44012 | AH27: Proposed accountable role; individual to be designated
A28: R-024 | B28: I3-G-01 | C28: Untested arrangements fail under load or during recovery | D28: Infrastructure | E28: 2.3 | F28: G | G28: Historical classification | H28: Consolidated | I28: Capacity and recovery tests are absent, inadequate or not acted upon. | J28: A critical arrangement fails when stressed or when recovery is required. | K28: Disruption lasts longer than expected and essential obligations may be threatened. | L28: Assurance of capacity and recovery | M28: 2020-04-01 to 2020-06-30 | P28: =IF(AD28="Consolidated","Consolidated",IF(OR(N28="",O28=""),"Not assessed",INDEX('Assessment Guide'!$B$5:$F$9,N28,O28))) -> Consolidated | Q28: Untested arrangements create uncertainty, not a certain failure. Demand or recovery activation must also occur. | R28: Major reflects failure of a critical arrangement; overlaps with R-021, R-022 and R-027 require review. | S28: Case: third-party cloud backup, hosting and security advice. Assessment assumption: firewalls, email scanning and minimum-privilege access operate as basic office safeguards. | T28: Mixed evidence: case arrangements plus explicit assessment assumptions; see Evidence and experience. | U28: Basic safeguards may reduce exposure. Their remote-work coverage, integrity protection, monitoring and restoration performance are unverified. | V28: Test plans, results, remediation and recovery evidence are not documented. | W28: Not assessed separately | X28: Consolidated, not resolved. Current assessment is held in R-021; R-022; R-025. Original content and ratings remain in source/history sheets. | Y28: Controllability is substantial for the identified internal cause, subject to available resources and verified implementation. | Z28: Sustain assurance of capacity and recovery as part of meeting essential service and policyholder obligations. Business necessity does not itself make the exposure tolerable. | AA28: Consequences may extend beyond three months; reassess during weekly reviews. Initial likelihood horizon ends 2020-06-30; later information belongs to dated reviews. | AB28: Network Manager | AC28: Business outline(1).pdf: The case confirms cloud backup, hosting and security consultants (pp. 6–7). Scope, security configuration and successful recovery are unspecified. No internal incident history is verified. Only evidence available by 2020-04-01 can support the initial assessment. | AD28: Consolidated | AE28: R-021; R-022; R-025 | AF28: 43922 | AG28: 44012 | AH28: Proposed accountable role; individual to be designated
A29: R-025 | B29: I4-G-02 | C29: Service restoration exceeds the required timeframe | D29: Infrastructure | E29: 2.4 | F29: G | G29: Current classification | H29: Initial assessment; conclusions provisional | I29: Remote coordination difficulties, unsuitable recovery procedures and untested recovery arrangements impede restoration. | J29: Following a service disruption, essential services cannot be restored within the required timeframe. | K29: Prolonged outages and backlogs threaten claims handling, premium collection and customer support, increasing costs and customer harm. This assesses recovery performance following a disruption, not the initial failure itself. | L29: Staff coordination and recovery | M29: 2020-04-01 to 2020-06-30 | N29: 3 | O29: 4 | P29: =IF(AD29="Consolidated","Consolidated",IF(OR(N29="",O29=""),"Not assessed",INDEX('Assessment Guide'!$B$5:$F$9,N29,O29))) -> High | Q29: Possible: both a disruption and unsuccessful or delayed recovery must occur within the horizon. Remote coordination and untested arrangements support concern, but no recovery performance history is supplied. | R29: Proposed Major, increased from Moderate: the consolidated event includes failure of recovery procedures and tests, potentially extending disruption across essential services. The required recovery timeframe still needs definition. | S29: Case: third-party cloud backup, hosting and security advice. Assessment assumption: firewalls, email scanning and minimum-privilege access operate as basic office safeguards. | T29: Mixed evidence: case arrangements plus explicit assessment assumptions; see Evidence and experience. | U29: Basic safeguards may reduce exposure. Their remote-work coverage, integrity protection, monitoring and restoration performance are unverified. | V29: Confirm recovery procedures, coordination roles, tested restoration of cloud backups, recovery objectives and evidence of exercises. R-024 recovery-testing and R-027 procedure gaps are incorporated here. | W29: Not tolerable | X29: Not tolerable on the assumed inability to restore essential services within required timeframes. Cloud backup alone does not prove recoverability; test and procedure weaknesses from consolidated records remain relevant. | Y29: Controllability is substantial for the identified internal cause, subject to available resources and verified implementation. | Z29: Sustain staff coordination and recovery as part of meeting essential service and policyholder obligations. Business necessity does not itself make the exposure tolerable. | AA29: Consequences may extend beyond three months; reassess during weekly reviews. Initial likelihood horizon ends 2020-06-30; later information belongs to dated reviews. | AB29: Network Manager | AC29: Business outline(1).pdf: The case confirms cloud backup, hosting and security consultants (pp. 6–7). Scope, security configuration and successful recovery are unspecified. No internal incident history is verified. Only evidence available by 2020-04-01 can support the initial assessment. | AD29: Active | AF29: 43922 | AG29: 44012 | AH29: Proposed accountable role; individual to be designated
A30: R-026 | B30: I4-S-01 | C30: A critical supplier reduces or ends service | D30: Infrastructure | E30: 2.4 | F30: S | G30: Current classification | H30: Initial assessment; conclusions provisional | I30: Supplier staffing, operating restrictions or financial pressure reduce capacity. | J30: A provider fails to deliver an essential contracted service. | K30: Operations may be interrupted, replacement costs incurred and confidential records or communications left unmanaged. | L30: Critical suppliers | M30: 2020-04-01 to 2020-06-30 | N30: 3 | O30: 4 | P30: =IF(AD30="Consolidated","Consolidated",IF(OR(N30="",O30=""),"Not assessed",INDEX('Assessment Guide'!$B$5:$F$9,N30,O30))) -> High | Q30: Pandemic pressure makes supplier disruption plausible; individual provider resilience is unknown. | R30: Major assumes an essential service with no ready alternative. Noncritical delays would be lower. | S30: Case: third-party service relationships, including backup, hosting, security advice and legal services. No supplier continuity assurance is specified. | T30: Mixed evidence: case arrangements plus explicit assessment assumptions; see Evidence and experience. | U30: Access to providers is not proof of resilience. Contracts, alternative capacity and service continuity need assessment. | V30: Continuity commitments, alternatives, service monitoring and handover arrangements are unverified. | W30: Not tolerable | X30: Not tolerable for an essential supplier failure with no workable substitute on the assessed assumption. Routine noncritical supplier delays would warrant a different decision. | Y30: Controllability is partial: internal preparation and decisions can reduce exposure, while external conditions may remain beyond our control. | Z30: Sustain critical suppliers as part of meeting essential service and policyholder obligations. Business necessity does not itself make the exposure tolerable. | AA30: Consequences may extend beyond three months; reassess during weekly reviews. Initial likelihood horizon ends 2020-06-30; later information belongs to dated reviews. | AB30: Designated Executive Director | AC30: Business outline(1).pdf: The case confirms cloud backup, hosting and security consultants (pp. 6–7). Scope, security configuration and successful recovery are unspecified. No internal incident history is verified. Only evidence available by 2020-04-01 can support the initial assessment. | AD30: Active | AF30: 43922 | AG30: 44012 | AH30: Proposed accountable role; individual to be designated
A31: R-027 | B31: I4-G-01 | C31: Recovery cannot be coordinated during remote work | D31: Infrastructure | E31: 2.4 | F31: G | G31: Historical classification | H31: Consolidated | I31: Crisis and recovery procedures are missing, unsuitable or not implemented for remote operations. | J31: The organization cannot coordinate an effective response to a significant disruption. | K31: Recovery is prolonged across essential services, threatening obligations and customer confidence. | L31: Recovery governance and dependencies | M31: 2020-04-01 to 2020-06-30 | P31: =IF(AD31="Consolidated","Consolidated",IF(OR(N31="",O31=""),"Not assessed",INDEX('Assessment Guide'!$B$5:$F$9,N31,O31))) -> Consolidated | Q31: A disruption and ineffective coordination must coincide; a missing procedure is not automatically a likely event. | R31: Major assumes a substantial delay in recovery; avoid counting the same outage independently several times. | S31: Case: third-party cloud backup, hosting and security advice. Assessment assumption: firewalls, email scanning and minimum-privilege access operate as basic office safeguards. | T31: Mixed evidence: case arrangements plus explicit assessment assumptions; see Evidence and experience. | U31: Basic safeguards may reduce exposure. Their remote-work coverage, integrity protection, monitoring and restoration performance are unverified. | V31: Remote recovery procedures, exercises, authority and fallback arrangements need verification. | W31: Not assessed separately | X31: Consolidated, not resolved. Current assessment is held in R-025. Original content and ratings remain in source/history sheets. | Y31: Controllability is substantial for the identified internal cause, subject to available resources and verified implementation. | Z31: Sustain recovery governance and dependencies as part of meeting essential service and policyholder obligations. Business necessity does not itself make the exposure tolerable. | AA31: Consequences may extend beyond three months; reassess during weekly reviews. Initial likelihood horizon ends 2020-06-30; later information belongs to dated reviews. | AB31: Network Manager | AC31: Business outline(1).pdf: The case confirms cloud backup, hosting and security consultants (pp. 6–7). Scope, security configuration and successful recovery are unspecified. No internal incident history is verified. Only evidence available by 2020-04-01 can support the initial assessment. | AD31: Consolidated | AE31: R-025 | AF31: 43922 | AG31: 44012 | AH31: Proposed accountable role; individual to be designated
A32: R-028 | B32: R1-P-01 | C32: Claims and enquiries exceed response capacity | D32: Reputation | E32: 3.1 | F32: P | G32: Current classification | H32: Initial assessment; conclusions provisional | I32: A surge in claims, related enquiries and coverage disputes exceeds planned processing capacity. | J32: Claims-related workloads exceed processing capacity even when planned staffing is available. | K32: Claims handling and related responses are delayed, increasing backlogs, complaints and customer harm. Separate from reduced staffing at normal demand in R-035. | L32: Claims capacity and customer trust | M32: 2020-04-01 to 2020-06-30 | N32: 4 | O32: 3 | P32: =IF(AD32="Consolidated","Consolidated",IF(OR(N32="",O32=""),"Not assessed",INDEX('Assessment Guide'!$B$5:$F$9,N32,O32))) -> High | Q32: A demand surge is likely, but actual volumes and capacity are not established. | R32: Moderate assumes delays can be managed without sustained failure of obligations; severe vulnerable-customer harm would be higher. | S32: Case: customer-service roles and digital service channels. Assessment assumption: a customer incentive fund is available. | T32: Mixed evidence: case arrangements plus explicit assessment assumptions; see Evidence and experience. | U32: Incentives can assist recovery after a failure but do not prevent workload or staffing disruption. | V32: Baseline response times, workloads, service limits and contingency staffing are unverified. | W32: Not tolerable | X32: Not tolerable if surge demand produces material claims delays beyond the organization’s accepted service position. A customer incentive fund does not address processing capacity. Exact limits remain to be defined. | Y32: Controllability is substantial for the identified internal cause, subject to available resources and verified implementation. | Z32: Sustain claims capacity and customer trust as part of meeting essential service and policyholder obligations. Business necessity does not itself make the exposure tolerable. | AA32: Consequences may extend beyond three months; reassess during weekly reviews. Initial likelihood horizon ends 2020-06-30; later information belongs to dated reviews. | AB32: Claims Manager | AC32: Business outline(1).pdf: The case confirms a small workforce and functional roles (pp. 6–7), but no trained backup or staff-continuity arrangements. The case confirms products, distribution channels and customer-facing systems (pp. 2, 4–5), but not market-research or retention-control operation. No internal incident history is verified. Only evidence available by 2020-04-01 can support the initial assessment. | AD32: Active | AF32: 43922 | AG32: 44012 | AH32: Proposed accountable role; individual to be designated
A33: R-029 | B33: R1-C-01 | C33: Customers in difficulty receive insensitive treatment | D33: Reputation | E33: 3.1 | F33: C | G33: Current classification | H33: Initial assessment; conclusions provisional | I33: Pressure, poor judgment or inappropriate behaviour affects customer interactions. | J33: Employees treat financially vulnerable customers insensitively. | K33: Complaints and loss of trust may increase, reducing retention and requiring remediation. | L33: Fair customer treatment | M33: 2020-04-01 to 2020-06-30 | N33: 3 | O33: 3 | P33: =IF(AD33="Consolidated","Consolidated",IF(OR(N33="",O33=""),"Not assessed",INDEX('Assessment Guide'!$B$5:$F$9,N33,O33))) -> Moderate | Q33: Stress makes inappropriate interactions plausible, but no conduct history establishes likely occurrence. | R33: Moderate assumes repeated or meaningful customer impacts, not isolated discourtesy without harm. | S33: Case: communication roles and legal services. Assessment assumption: social-media crisis templates are available. | T33: Mixed evidence: case arrangements plus explicit assessment assumptions; see Evidence and experience. | U33: Templates and advice may support communication. Accuracy, timely updates and checks across channels are not demonstrated. | V33: Communication guidance, training, complaint review and supervisory checks need confirmation. | W33: Not tolerable | X33: Not tolerable for avoidable insensitive treatment causing meaningful harm to vulnerable customers. Workload pressure does not justify conduct inconsistent with fair treatment. | Y33: Controllability is substantial for the identified internal cause, subject to available resources and verified implementation. | Z33: Sustain fair customer treatment as part of meeting essential service and policyholder obligations. Business necessity does not itself make the exposure tolerable. | AA33: Consequences may extend beyond three months; reassess during weekly reviews. Initial likelihood horizon ends 2020-06-30; later information belongs to dated reviews. | AB33: Customer Service Manager | AC33: Business outline(1).pdf: The case confirms a Marketing Manager, customer-service roles and legal services (pp. 6–7), but not communication templates or approval checks. No internal incident history is verified. Only evidence available by 2020-04-01 can support the initial assessment. | AD33: Active | AF33: 43922 | AG33: 44012 | AH33: Proposed accountable role; individual to be designated
A34: R-030 | B34: R2-G-01 | C34: Coverage misinformation remains uncorrected | D34: Reputation | E34: 3.2 | F34: G | G34: Current classification | H34: Initial assessment; conclusions provisional | I34: Information verification and communication coordination are inadequate. | J34: Customers receive or rely on inaccurate or uncorrected information about their insurance coverage. | K34: Customers may misunderstand their protection, make poorly informed decisions or dispute claims outcomes, damaging trust and increasing remediation costs. | L34: Accurate information and trust | M34: 2020-04-01 to 2020-06-30 | N34: 3 | O34: 4 | P34: =IF(AD34="Consolidated","Consolidated",IF(OR(N34="",O34=""),"Not assessed",INDEX('Assessment Guide'!$B$5:$F$9,N34,O34))) -> High | Q34: Rapid changes and misinformation make confusion plausible; deliberate deception is not assumed. | R34: Major assumes material misinformation affecting many customers or important coverage decisions. | S34: Case: communication roles and legal services. Assessment assumption: social-media crisis templates are available. | T34: Mixed evidence: case arrangements plus explicit assessment assumptions; see Evidence and experience. | U34: Templates and advice may support communication. Accuracy, timely updates and checks across channels are not demonstrated. | V34: Crisis templates are reported, but accuracy checks, ownership and misinformation procedures are unverified. | W34: Not tolerable | X34: Not tolerable for material coverage misinformation leading customers to make harmful decisions. Templates alone do not demonstrate accuracy and effective correction. | Y34: Controllability is substantial for the identified internal cause, subject to available resources and verified implementation. | Z34: Sustain accurate information and trust as part of meeting essential service and policyholder obligations. Business necessity does not itself make the exposure tolerable. | AA34: Consequences may extend beyond three months; reassess during weekly reviews. Initial likelihood horizon ends 2020-06-30; later information belongs to dated reviews. | AB34: Underwriting Manager | AC34: Business outline(1).pdf: The case confirms a Marketing Manager, customer-service roles and legal services (pp. 6–7), but not communication templates or approval checks. No internal incident history is verified. Only evidence available by 2020-04-01 can support the initial assessment. | AD34: Active | AF34: 43922 | AG34: 44012 | AH34: Proposed accountable role; individual to be designated
A35: R-031 | B35: R2-P-01 | C35: Remote-work stress impairs employee wellbeing | D35: Reputation | E35: 3.2 | F35: P | G35: Current classification | H35: Initial assessment; conclusions provisional | I35: Isolation, changed routines and inadequate support increase sustained stress. | J35: Employees experience wellbeing difficulties that impair their ability to work safely and effectively. | K35: Absence, reduced performance and service delays may occur alongside harm to employees. | L35: Employee wellbeing and staffing | M35: 2020-04-01 to 2020-06-30 | N35: 4 | O35: 3 | P35: =IF(AD35="Consolidated","Consolidated",IF(OR(N35="",O35=""),"Not assessed",INDEX('Assessment Guide'!$B$5:$F$9,N35,O35))) -> High | Q35: A sudden transition and isolation make wellbeing difficulties likely, with individual effects uncertain. | R35: Moderate assumes material but manageable effects; serious individual harm requires separate consideration. | S35: No staff-continuity or wellbeing control is specified in the case. Assessment assumption: assumed preparation gaps apply at the assessment date. | T35: Mixed evidence: case arrangements plus explicit assessment assumptions; see Evidence and experience. | U35: Existing staffing is capacity, not a tested continuity control. Backup coverage and support effectiveness remain unverified. | V35: Support availability, workload checks and access to assistance are not evidenced. | W35: Not tolerable | X35: Not tolerable on the assumption that material employee wellbeing harms persist without adequate support. The need for remote work does not justify leaving this controllable exposure unmanaged. | Y35: Controllability is substantial for the identified internal cause, subject to available resources and verified implementation. | Z35: Sustain employee wellbeing and staffing as part of meeting essential service and policyholder obligations. Business necessity does not itself make the exposure tolerable. | AA35: Consequences may extend beyond three months; reassess during weekly reviews. Initial likelihood horizon ends 2020-06-30; later information belongs to dated reviews. | AB35: Designated HR lead | AC35: Business outline(1).pdf: The case confirms a small workforce and functional roles (pp. 6–7), but no trained backup or staff-continuity arrangements. No internal incident history is verified. Only evidence available by 2020-04-01 can support the initial assessment. | AD35: Active | AF35: 43922 | AG35: 44012 | AH35: Proposed accountable role; individual to be designated
A36: R-032 | B36: R3-P-01 | C36: Workload pressure causes processing and record errors | D36: Reputation | E36: 3.3 | F36: P | G36: Current classification | H36: Initial assessment; conclusions provisional | I36: High workloads, unfamiliar tasks and fatigue increase mistakes. | J36: Claims or customer records are processed incorrectly or incompletely. | K36: Rework, delayed payments, customer harm and failures to evidence obligations may result. | L36: Accurate processing and records | M36: 2020-04-01 to 2020-06-30 | N36: 4 | O36: 3 | P36: =IF(AD36="Consolidated","Consolidated",IF(OR(N36="",O36=""),"Not assessed",INDEX('Assessment Guide'!$B$5:$F$9,N36,O36))) -> High | Q36: Pressure during transition makes processing errors likely without credited controls. | R36: Moderate assumes remediable errors; systemic or high-value errors could be Major. | S36: Case: record keeping and database administration. Assessment assumption: an operational audit trail is maintained. | T36: Mixed evidence: case arrangements plus explicit assessment assumptions; see Evidence and experience. | U36: Records support detection and investigation. They do not demonstrate preventive approval, fraud detection or counterparty protection. | V36: Audit trails are reported, but prevention, quality checks and error monitoring are unverified. | W36: Not tolerable | X36: Not tolerable for material processing and record failures where preventive or quality controls are assumed inadequate. Records after the event do not establish acceptable ongoing accuracy. | Y36: Controllability is substantial for the identified internal cause, subject to available resources and verified implementation. | Z36: Sustain accurate processing and records as part of meeting essential service and policyholder obligations. Business necessity does not itself make the exposure tolerable. | AA36: Consequences may extend beyond three months; reassess during weekly reviews. Initial likelihood horizon ends 2020-06-30; later information belongs to dated reviews. | AB36: Claims Manager | AC36: Business outline(1).pdf: The case confirms record keeping and database administration (p. 6), but not an effective transaction audit trail or approval process. No internal incident history is verified. Only evidence available by 2020-04-01 can support the initial assessment. | AD36: Active | AF36: 43922 | AG36: 44012 | AH36: Proposed accountable role; individual to be designated
A37: R-033 | B37: R3-T-01 | C37: Widespread sensitive customer information is exposed | D37: Reputation | E37: 3.3 | F37: T | G37: Current classification | H37: Initial assessment; conclusions provisional | I37: Remote-access or information-handling weaknesses expose sensitive data. | J37: Unauthorized access or disclosure exposes sensitive information relating to a substantial number of customers. | K37: Widespread sensitive-information exposure may cause serious customer harm, substantial remediation and lasting loss of trust. System disruption alone is assessed under R-020. | L37: Customer information and trust | M37: 2020-04-01 to 2020-06-30 | N37: 3 | O37: 5 | P37: =IF(AD37="Consolidated","Consolidated",IF(OR(N37="",O37=""),"Not assessed",INDEX('Assessment Guide'!$B$5:$F$9,N37,O37))) -> Extreme | Q37: Possible within April 1–June 30, 2020 is retained as a provisional judgment. Narrowing the event to widespread serious-harm disclosure does not alone justify a lower likelihood band. Accessible data volumes, safeguards and breach pathways require verification. | R37: Severe only for widespread sensitive-data exposure causing serious customer harm. This is not a blanket score for every disclosure and is not justified merely by low appetite. | S37: Case: third-party cloud backup, hosting and security advice. Assessment assumption: firewalls, email scanning and minimum-privilege access operate as basic office safeguards. | T37: Mixed evidence: case arrangements plus explicit assessment assumptions; see Evidence and experience. | U37: Basic safeguards may reduce exposure. Their remote-work coverage, integrity protection, monitoring and restoration performance are unverified. | V37: Access restrictions and legal advice are reported; coverage, testing and incident procedures need verification. | W37: Not tolerable | X37: Not tolerable for the defined widespread serious-harm disclosure scenario on assumed inadequate safeguards. This conclusion concerns the scenario’s consequences and control gaps, not all minor information incidents. | Y37: Controllability is substantial for the identified internal cause, subject to available resources and verified implementation. | Z37: Sustain customer information and trust as part of meeting essential service and policyholder obligations. Business necessity does not itself make the exposure tolerable. | AA37: Consequences may extend beyond three months; reassess during weekly reviews. Initial likelihood horizon ends 2020-06-30; later information belongs to dated reviews. | AB37: Network Manager | AC37: Business outline(1).pdf: The case confirms cloud backup, hosting and security consultants (pp. 6–7). Scope, security configuration and successful recovery are unspecified. No internal incident history is verified. Only evidence available by 2020-04-01 can support the initial assessment. | AD37: Active | AF37: 43922 | AG37: 44012 | AH37: Proposed accountable role; individual to be designated
A38: R-034 | B38: R3-G-01 | C38: Applicable obligations are missed | D38: Reputation | E38: 3.3 | F38: G | G38: Current classification | H38: Initial assessment; conclusions provisional | I38: Responsibility and procedures for identifying applicable requirements are incomplete. | J38: The organization fails to meet an obligation it has not identified or understood. | K38: Remediation, regulatory action, customer harm and reputational damage may follow. | L38: Compliance knowledge and accountability | M38: 2020-04-01 to 2020-06-30 | N38: 2 | O38: 4 | P38: =IF(AD38="Consolidated","Consolidated",IF(OR(N38="",O38=""),"Not assessed",INDEX('Assessment Guide'!$B$5:$F$9,N38,O38))) -> High | Q38: An unidentified requirement could be missed; actual applicability and evidence of omissions remain uncertain. | R38: Major assumes a material obligation. No particular regulator is assumed to supervise every activity. | S38: Case: record keeping and database administration. Assessment assumption: an operational audit trail is maintained. | T38: Mixed evidence: case arrangements plus explicit assessment assumptions; see Evidence and experience. | U38: Records support detection and investigation. They do not demonstrate preventive approval, fraud detection or counterparty protection. | V38: Requirement mapping, legal review scope and compliance ownership need confirmation. | W38: Not tolerable | X38: Not tolerable if applicable material obligations remain unidentified. Legal services provide a resource but do not establish a complete and effective requirements assessment. | Y38: Controllability is substantial for the identified internal cause, subject to available resources and verified implementation. | Z38: Sustain compliance knowledge and accountability as part of meeting essential service and policyholder obligations. Business necessity does not itself make the exposure tolerable. | AA38: Consequences may extend beyond three months; reassess during weekly reviews. Initial likelihood horizon ends 2020-06-30; later information belongs to dated reviews. | AB38: Designated Executive Director | AC38: Business outline(1).pdf: The case confirms record keeping and database administration (p. 6), but not an effective transaction audit trail or approval process. No internal incident history is verified. Only evidence available by 2020-04-01 can support the initial assessment. | AD38: Active | AF38: 43922 | AG38: 44012 | AH38: Proposed accountable role; individual to be designated
A39: R-035 | B39: R4-P-01 | C39: Staff shortages delay routine customer service | D39: Reputation | E39: 3.4 | F39: P | G39: Current classification | H39: Initial assessment; conclusions provisional | I39: Absence or vacancies reduce staff available for normal customer-facing workloads. | J39: Customer support, policy administration and other customer-facing services cannot be maintained even at normal demand. | K39: Routine services are interrupted or delayed, reducing service quality and retention. This may compound the demand-driven claims pressure in R-028 but is independently possible. | L39: Customer service staffing | M39: 2020-04-01 to 2020-06-30 | N39: 4 | O39: 3 | P39: =IF(AD39="Consolidated","Consolidated",IF(OR(N39="",O39=""),"Not assessed",INDEX('Assessment Guide'!$B$5:$F$9,N39,O39))) -> High | Q39: Reduced staffing during pandemic disruption makes routine delays likely. | R39: Moderate assumes manageable delays. Keep distinct from R-028 only if routine service scope is meaningful. | S39: Case: customer-service roles and digital service channels. Assessment assumption: a customer incentive fund is available. | T39: Mixed evidence: case arrangements plus explicit assessment assumptions; see Evidence and experience. | U39: Incentives can assist recovery after a failure but do not prevent workload or staffing disruption. | V39: Service coverage, queue monitoring and minimum staffing arrangements need verification. | W39: Not tolerable | X39: Not tolerable on the assumed inability to cover essential customer-service roles at normal demand. Minor delays within accepted limits would be assessed differently. | Y39: Controllability is substantial for the identified internal cause, subject to available resources and verified implementation. | Z39: Sustain customer service staffing as part of meeting essential service and policyholder obligations. Business necessity does not itself make the exposure tolerable. | AA39: Consequences may extend beyond three months; reassess during weekly reviews. Initial likelihood horizon ends 2020-06-30; later information belongs to dated reviews. | AB39: Customer Service Manager | AC39: Business outline(1).pdf: The case confirms a small workforce and functional roles (pp. 6–7), but no trained backup or staff-continuity arrangements. The case confirms products, distribution channels and customer-facing systems (pp. 2, 4–5), but not market-research or retention-control operation. No internal incident history is verified. Only evidence available by 2020-04-01 can support the initial assessment. | AD39: Active | AF39: 43922 | AG39: 44012 | AH39: Proposed accountable role; individual to be designated
A40: R-036 | B40: R4-G-01 | C40: Service expectations are communicated unclearly | D40: Reputation | E40: 3.4 | F40: G | G40: Current classification | H40: Initial assessment; conclusions provisional | I40: Communication procedures do not keep service timelines, availability and support-channel information consistent. | J40: Customers receive unclear or inconsistent information about service availability, processing times or how to access support. | K40: Unmet expectations, repeated enquiries and complaints increase service pressure and reduce confidence. Coverage accuracy is assessed in R-030. | L40: Consistent service communication | M40: 2020-04-01 to 2020-06-30 | N40: 3 | O40: 3 | P40: =IF(AD40="Consolidated","Consolidated",IF(OR(N40="",O40=""),"Not assessed",INDEX('Assessment Guide'!$B$5:$F$9,N40,O40))) -> Moderate | Q40: Multiple channels and changing conditions make inconsistent messages plausible. | R40: Moderate assumes remediable confusion; material coverage misinformation is assessed in R-030. | S40: Case: communication roles and legal services. Assessment assumption: social-media crisis templates are available. | T40: Mixed evidence: case arrangements plus explicit assessment assumptions; see Evidence and experience. | U40: Templates and advice may support communication. Accuracy, timely updates and checks across channels are not demonstrated. | V40: Message approval, service updates and consistency checks are unverified. | W40: Not tolerable | X40: Not tolerable where assumed communication gaps repeatedly create material unmet expectations and customer harm. A low-impact isolated misunderstanding is outside this scenario. | Y40: Controllability is substantial for the identified internal cause, subject to available resources and verified implementation. | Z40: Sustain consistent service communication as part of meeting essential service and policyholder obligations. Business necessity does not itself make the exposure tolerable. | AA40: Consequences may extend beyond three months; reassess during weekly reviews. Initial likelihood horizon ends 2020-06-30; later information belongs to dated reviews. | AB40: Customer Service Manager | AC40: Business outline(1).pdf: The case confirms a Marketing Manager, customer-service roles and legal services (pp. 6–7), but not communication templates or approval checks. No internal incident history is verified. Only evidence available by 2020-04-01 can support the initial assessment. | AD40: Active | AF40: 43922 | AG40: 44012 | AH40: Proposed accountable role; individual to be designated
A41: R-037 | B41: M1-E-01 | C41: Households reduce or cancel coverage | D41: Marketing | E41: 4.1 | F41: E | G41: Current classification | H41: Initial assessment; conclusions provisional | I41: Income loss and financial uncertainty reduce customers' ability to pay. Delayed or insufficient public assistance may prolong household affordability pressure. | J41: Individual customers defer payments, reduce cover or cancel policies. | K41: Premium income and retention decline, weakening funds available for operations. | L41: Premium income and customer retention | M41: 2020-04-01 to 2020-06-30 | N41: 4 | O41: 3 | P41: =IF(AD41="Consolidated","Consolidated",IF(OR(N41="",O41=""),"Not assessed",INDEX('Assessment Guide'!$B$5:$F$9,N41,O41))) -> High | Q41: Pandemic-related income pressure makes some reductions likely; portfolio-specific lapse rates are unknown. Public assistance may affect the duration of pressure; no particular program or eligibility is assumed. | R41: Moderate assumes losses are manageable across the book; widespread lapse would be more severe. | S41: Assessment assumption: financial modelling, market research and customer incentives operate. None is specified as a tested control in the case. | T41: Mixed evidence: case arrangements plus explicit assessment assumptions; see Evidence and experience. | U41: These may support adaptation and retention, but cannot prevent customers’ financial difficulties or prove revenue resilience. | V41: Lapse forecasts, affordability arrangements and retention effectiveness need confirmation. | W41: Tolerable | X41: Tolerable provisionally as an unavoidable, moderate commercial exposure to household affordability pressure, assuming premium losses remain within financial capacity and customers are treated appropriately. This assumption must be tested against portfolio forecasts. Assess combined premium-income effects across R-037, R-038 and R-040; individual affordability does not establish aggregate capacity. | Y41: Controllability is partial: internal preparation and decisions can reduce exposure, while external conditions may remain beyond our control. | Z41: Sustain premium income and customer retention as part of meeting essential service and policyholder obligations. Business necessity does not itself make the exposure tolerable. | AA41: Consequences may extend beyond three months; reassess during weekly reviews. Initial likelihood horizon ends 2020-06-30; later information belongs to dated reviews. | AB41: Marketing Manager | AC41: Business outline(1).pdf: The case confirms products, distribution channels and customer-facing systems (pp. 2, 4–5), but not market-research or retention-control operation. No internal incident history is verified. Only evidence available by 2020-04-01 can support the initial assessment. | AD41: Active | AF41: 43922 | AG41: 44012 | AH41: Proposed accountable role; individual to be designated
A42: R-038 | B42: M1-E-02 | C42: Small-business clients reduce, defer or cancel coverage | D42: Marketing | E42: 4.1 | F42: E | G42: Current classification | H42: Initial assessment; conclusions provisional | I42: Pandemic revenue losses or closures reduce small-business clients’ ability to fund premiums. Delayed or insufficient public assistance may prolong this pressure. | J42: Small-business clients defer premium payments, reduce coverage or cancel policies. | K42: Premium income and customer retention decline. Business-client cover is confirmed as a segment, but particular policy types and coverage terms are unspecified. | L42: Customer affordability and premium income | M42: 2020-04-01 to 2020-06-30 | N42: 3 | O42: 3 | P42: =IF(AD42="Consolidated","Consolidated",IF(OR(N42="",O42=""),"Not assessed",INDEX('Assessment Guide'!$B$5:$F$9,N42,O42))) -> Moderate | Q42: Possible: the case confirms more than 100 small-business clients (Business outline, p. 2). Revenue disruption could affect their payments; concentration, premium value and actual lapse rates are unknown. | R42: Moderate provisional judgment: a meaningful segment may be affected, but its premium share is not supplied. Do not substitute business owners’ personal policies for the confirmed business-client segment. | S42: Assessment assumption: financial modelling, market research and customer incentives operate. None is specified as a tested control in the case. | T42: Mixed evidence: case arrangements plus explicit assessment assumptions; see Evidence and experience. | U42: These may support adaptation and retention, but cannot prevent customers’ financial difficulties or prove revenue resilience. | V42: Confirm business-client premium exposure, policy terms and affordability arrangements. Do not assume business-interruption cover or public-program eligibility. | W42: Tolerable | X42: Tolerable provisionally as moderate exposure to the confirmed small-business segment, assuming reductions do not threaten financial capacity and treatment of customers remains appropriate. The segment’s premium concentration is unverified. Assess combined premium-income effects across R-037, R-038 and R-040; individual affordability does not establish aggregate capacity. | Y42: Controllability is partial: internal preparation and decisions can reduce exposure, while external conditions may remain beyond our control. | Z42: Sustain customer affordability and premium income as part of meeting essential service and policyholder obligations. Business necessity does not itself make the exposure tolerable. | AA42: Consequences may extend beyond three months; reassess during weekly reviews. Initial likelihood horizon ends 2020-06-30; later information belongs to dated reviews. | AB42: Marketing Manager | AC42: Business outline(1).pdf: The case confirms products, distribution channels and customer-facing systems (pp. 2, 4–5), but not market-research or retention-control operation. No internal incident history is verified. Only evidence available by 2020-04-01 can support the initial assessment. | AD42: Active | AF42: 43922 | AG42: 44012 | AH42: Proposed accountable role; individual to be designated
A43: R-039 | B43: M1-E-03 | C43: Travel demand and auto premium income fall | D43: Marketing | E43: 4.1 | F43: E | G43: Current classification | H43: Tolerability awaiting evidence | I43: Travel restrictions and reduced driving change insurance needs and expectations. | J43: Travel sales decline sharply and auto customers seek lower premiums or reduced cover. | K43: Revenue and product mix deteriorate, potentially requiring significant resource adjustment. | L43: Product revenue and diversification | M43: 2020-04-01 to 2020-06-30 | N43: 5 | O43: 4 | P43: =IF(AD43="Consolidated","Consolidated",IF(OR(N43="",O43=""),"Not assessed",INDEX('Assessment Guide'!$B$5:$F$9,N43,O43))) -> Extreme | Q43: These demand changes are highly plausible at pandemic onset; exact timing and size remain assumptions. | R43: Major assumes material concentration in affected lines. Travel sales are not assumed to stop entirely. | S43: Assessment assumption: financial modelling, market research and customer incentives operate. None is specified as a tested control in the case. | T43: Mixed evidence: case arrangements plus explicit assessment assumptions; see Evidence and experience. | U43: These may support adaptation and retention, but cannot prevent customers’ financial difficulties or prove revenue resilience. | V43: Product forecasts, revenue sensitivity and retention measures are unverified. | W43: Awaiting assessment | X43: Awaiting assessment: the case does not quantify the exposure and available financial capacity sufficiently to decide whether the remaining risk fits appetite. Product forecasts, revenue sensitivity and retention measures are unverified. Continued operations require this assessment; a High or Extreme inherent rating alone is not a tolerability decision. | Y43: Controllability is partial: internal preparation and decisions can reduce exposure, while external conditions may remain beyond our control. | Z43: Sustain product revenue and diversification as part of meeting essential service and policyholder obligations. Business necessity does not itself make the exposure tolerable. | AA43: Consequences may extend beyond three months; reassess during weekly reviews. Initial likelihood horizon ends 2020-06-30; later information belongs to dated reviews. | AB43: Marketing Manager | AC43: Business outline(1).pdf: The case confirms products, distribution channels and customer-facing systems (pp. 2, 4–5), but not market-research or retention-control operation. No internal incident history is verified. Only evidence available by 2020-04-01 can support the initial assessment. | AD43: Active | AF43: 43922 | AG43: 44012 | AH43: Proposed accountable role; individual to be designated
... A46: R-042 | B46: I4-S-02 | C46: Nonfinancial support sought from Tiva is unavailable | D46: Infrastructure | E46: 2.4 | F46: S | G46: Current classification | H46: Initial assessment; conclusions provisional | I46: Competing demands across Tiva constrain specialist expertise, technical assistance or independent review. | J46: Nonfinancial support sought from Tiva is unavailable or delayed when needed. | K46: Risk assessment or operational improvements may be delayed while ITrustU uses internal capacity or seeks alternatives. Committed support or essential dependence is not assumed. Financial support is R-002. | L46: Group support and strategic flexibility | M46: 2020-04-01 to 2020-06-30 | N46: 3 | O46: 3 | P46: =IF(AD46="Consolidated","Consolidated",IF(OR(N46="",O46=""),"Not assessed",INDEX('Assessment Guide'!$B$5:$F$9,N46,O46))) -> Moderate | Q46: Group pressure is plausible, but no group financial evidence supports a firm assessment. | R46: Proposed Moderate: unavailable advisory or technical help creates coordination and resourcing pressures, but no essential dependence is confirmed. Major would require evidence that missing expertise threatens essential obligations. | S46: Case: third-party service relationships, including backup, hosting, security advice and legal services. No supplier continuity assurance is specified. | T46: Mixed evidence: case arrangements plus explicit assessment assumptions; see Evidence and experience. | U46: Access to providers is not proof of resilience. Contracts, alternative capacity and service continuity need assessment. | V46: Confirm the support sought, internal skills and alternative providers. Review proposed relocation from M3 to I4 for nonfinancial provider continuity. | W46: Tolerable | X46: Tolerable provisionally only on the assumption that internal capability or alternative specialists can sustain essential work without Tiva assistance. If essential dependence is established, reassess magnitude and tolerability. | Y46: Controllability is partial: internal preparation and decisions can reduce exposure, while external conditions may remain beyond our control. | Z46: Sustain group support and strategic flexibility as part of meeting essential service and policyholder obligations. Business necessity does not itself make the exposure tolerable. | AA46: Consequences may extend beyond three months; reassess during weekly reviews. Initial likelihood horizon ends 2020-06-30; later information belongs to dated reviews. | AB46: Designated Executive Director | AC46: Business outline(1).pdf: The case confirms cloud backup, hosting and security consultants (pp. 6–7). Scope, security configuration and successful recovery are unspecified. No internal incident history is verified. Only evidence available by 2020-04-01 can support the initial assessment. | AD46: Active | AF46: 43922 | AG46: 44012 | AH46: Proposed accountable role; individual to be designated
A47: R-043 | B47: M3-E-03 | C47: Delayed public support prolongs customer affordability pressure | D47: Marketing | E47: 4.3 | F47: E | G47: Historical classification | H47: Consolidated | I47: Relief delivery delays, eligibility limits or processing problems affect customers. | J47: Customers do not receive expected public support in time to maintain insurance payments. | K47: Arrears, coverage reductions and cancellations increase. | L47: Customer income and premium continuity | M47: 2020-04-01 to 2020-06-30 | P47: =IF(AD47="Consolidated","Consolidated",IF(OR(N47="",O47=""),"Not assessed",INDEX('Assessment Guide'!$B$5:$F$9,N47,O47))) -> Consolidated | Q47: Support may be delayed or unavailable, but specific programs and eligibility cannot be assumed at an unspecified onset date. | R47: Moderate assumes a material customer segment is affected. This is a driver of R-037 and R-038. | S47: Assessment assumption: financial modelling, market research and customer incentives operate. None is specified as a tested control in the case. | T47: Mixed evidence: case arrangements plus explicit assessment assumptions; see Evidence and experience. | U47: These may support adaptation and retention, but cannot prevent customers’ financial difficulties or prove revenue resilience. | V47: Confirm scenario date, relevant programs and whether this warrants a separate risk record. | W47: Not assessed separately | X47: Consolidated, not resolved. Current assessment is held in R-037; R-038. Original content and ratings remain in source/history sheets. | Y47: Controllability is partial: internal preparation and decisions can reduce exposure, while external conditions may remain beyond our control. | Z47: Sustain customer income and premium continuity as part of meeting essential service and policyholder obligations. Business necessity does not itself make the exposure tolerable. | AA47: Consequences may extend beyond three months; reassess during weekly reviews. Initial likelihood horizon ends 2020-06-30; later information belongs to dated reviews. | AB47: Marketing Manager | AC47: Business outline(1).pdf: The case confirms products, distribution channels and customer-facing systems (pp. 2, 4–5), but not market-research or retention-control operation. No internal incident history is verified. Only evidence available by 2020-04-01 can support the initial assessment. | AD47: Consolidated | AE47: R-037; R-038 | AF47: 43922 | AG47: 44012 | AH47: Proposed accountable role; individual to be designated
A48: R-044 | B48: M4-S-01 | C48: Repair and material shortages delay claims settlement | D48: Marketing | E48: 4.4 | F48: S | G48: Current classification | H48: Initial assessment; conclusions provisional | I48: Supplier disruption restricts labour, parts, inspections or construction materials. | J48: Covered repairs take longer or cost more than expected. | K48: Claims costs and settlement times rise, reducing margins and customer satisfaction. | L48: Claims supply chain | M48: 2020-04-01 to 2020-06-30 | N48: 4 | O48: 3 | P48: =IF(AD48="Consolidated","Consolidated",IF(OR(N48="",O48=""),"Not assessed",INDEX('Assessment Guide'!$B$5:$F$9,N48,O48))) -> High | Q48: Pandemic restrictions make repair disruption likely, but supplier and claim-volume evidence is limited. | R48: Moderate assumes manageable increases. Widespread cost escalation may be Major. | S48: Case: third-party service relationships, including backup, hosting, security advice and legal services. No supplier continuity assurance is specified. | T48: Mixed evidence: case arrangements plus explicit assessment assumptions; see Evidence and experience. | U48: Access to providers is not proof of resilience. Contracts, alternative capacity and service continuity need assessment. | V48: Repair capacity, cost forecasts, alternatives and settlement arrangements are unverified. | W48: Tolerable | X48: Tolerable provisionally for manageable repair delays and cost increases, assuming essential settlement obligations remain achievable and financial capacity can absorb the change. Severe shortages or unacceptable customer harm would overturn this decision. | Y48: Controllability is partial: internal preparation and decisions can reduce exposure, while external conditions may remain beyond our control. | Z48: Sustain claims supply chain as part of meeting essential service and policyholder obligations. Business necessity does not itself make the exposure tolerable. | AA48: Consequences may extend beyond three months; reassess during weekly reviews. Initial likelihood horizon ends 2020-06-30; later information belongs to dated reviews. | AB48: Claims Manager | AC48: Business outline(1).pdf: The case confirms cloud backup, hosting and security consultants (pp. 6–7). Scope, security configuration and successful recovery are unspecified. No internal incident history is verified. Only evidence available by 2020-04-01 can support the initial assessment. | AD48: Active | AF48: 43922 | AG48: 44012 | AH48: Proposed accountable role; individual to be designated
A49: R-045 | B49: M2-G-01 | C49: Online services fail to meet customer expectations | D49: Marketing | E49: 4.2 | F49: G | G49: Current classification | H49: Initial assessment; conclusions provisional | I49: Digital service design and investment do not keep pace with changing customer needs. | J49: Customers find ITrustU's online services insufficient and choose competitors. | K49: New business and retention decline, weakening market position and premium income. | L49: Digital customer experience | M49: 2020-04-01 to 2020-06-30 | N49: 4 | O49: 3 | P49: =IF(AD49="Consolidated","Consolidated",IF(OR(N49="",O49=""),"Not assessed",INDEX('Assessment Guide'!$B$5:$F$9,N49,O49))) -> High | Q49: A rapid shift online makes a capability mismatch likely, but customer research is needed. | R49: Moderate assumes manageable losses. Network outages and capacity are assessed separately in Infrastructure. | S49: Assessment assumption: financial modelling, market research and customer incentives operate. None is specified as a tested control in the case. | T49: Mixed evidence: case arrangements plus explicit assessment assumptions; see Evidence and experience. | U49: These may support adaptation and retention, but cannot prevent customers’ financial difficulties or prove revenue resilience. | V49: Market research is reported; digital capability assessments and customer evidence need verification. | W49: Not tolerable | X49: Not tolerable on the assumption that a material digital-capability gap persistently undermines essential customer access and retention. Research without appropriate service capability does not address the exposure. | Y49: Controllability is substantial for the identified internal cause, subject to available resources and verified implementation. | Z49: Sustain digital customer experience as part of meeting essential service and policyholder obligations. Business necessity does not itself make the exposure tolerable. | AA49: Consequences may extend beyond three months; reassess during weekly reviews. Initial likelihood horizon ends 2020-06-30; later information belongs to dated reviews. | AB49: Marketing Manager | AC49: Business outline(1).pdf: The case confirms products, distribution channels and customer-facing systems (pp. 2, 4–5), but not market-research or retention-control operation. No internal incident history is verified. Only evidence available by 2020-04-01 can support the initial assessment. | AD49: Active | AF49: 43922 | AG49: 44012 | AH49: Proposed accountable role; individual to be designated

Sheet Assessment Guide
A2: Assessment criteria
A3: Assess event likelihood over the initial three months and the full credible consequences. Inherent ratings are assessed before credit for controls.
A4: Likelihood / Magnitude | B4: 1 | C4: 2 | D4: 3 | E4: 4 | F4: 5
A5: 1 | B5: Low | C5: Low | D5: Low | E5: Moderate | F5: High
A6: 2 | B6: Low | C6: Low | D6: Moderate | E6: High | F6: High
A7: 3 | B7: Low | C7: Moderate | D7: Moderate | E7: High | F7: Extreme
A8: 4 | B8: Low | C8: Moderate | D8: High | E8: Extreme | F8: Extreme
A9: 5 | B9: Moderate | C9: Moderate | D9: High | E9: Extreme | F9: Extreme
A12: Score | B12: Likelihood | C12: Three-month probability
A13: 1 | B13: Rare | C13: Less than 5%
A14: 2 | B14: Unlikely | C14: 5% to less than 20%
A15: 3 | B15: Possible | C15: 20% to less than 50%
A16: 4 | B16: Likely | C16: 50% to less than 80%
A17: 5 | B17: Almost certain | C17: 80% or greater
A20: Score | B20: Magnitude | C20: Meaning
A21: 1 | B21: Insignificant | C21: Minor effects handled through routine work, with negligible financial loss or disruption and no meaningful customer harm.
A22: 2 | B22: Minor | C22: Limited loss, disruption or complaints managed by the affected team without materially affecting essential services or obligations.
A23: 3 | B23: Moderate | C23: Noticeable impacts require coordination and some resource reallocation. Essential obligations remain achievable.
A24: 4 | B24: Major | C24: Substantial losses, prolonged disruption, serious information exposure or damage to confidence threaten essential obligations and require significant management intervention.
A25: 5 | B25: Severe | C25: Consequences threaten organizational viability or sustained essential services, or cause widespread serious customer harm.
A28: Source | B28: Label | C28: Primary cause
A29: P | B29: People | C29: Staff capacity, skills, availability or unintentional human error.
A30: T | B30: Technology | C30: Technical capacity, reliability or security weakness.
A31: S | B31: Suppliers and third parties | C31: Failure or limitation of a separate provider or group support entity.
A32: E | B32: External Conditions | C32: Economic, public-health, weather or other external conditions.
A33: G | B33: Governance and Processes | C33: Weak accountability, procedure design, oversight or work organization.
A34: C | B34: Conduct | C34: Deliberate deception, inappropriate behaviour or failure to follow established procedures.
A36: Use the highest credible consequence across FIRM, with a stated scenario. Appetite alone does not determine magnitude.
A37: Probability bands are judgment categories, not measured forecasts. Missing information does not by itself justify a likelihood score.
A38: Assess whether the event occurs from April 1 through June 30, 2020. Include consequences beyond that window. Introduce later evidence through dated reviews.
A39: Locate the category at the likelihood row and magnitude column. Do not multiply scores. Tolerability also considers controls, appetite, controllability and business necessity.
A40: Distinguish confirmed arrangements, assessment assumptions, undocumented controls and proposed improvements. Existence does not establish effectiveness.
A41: Each active risk has one proposed accountable organizational role; actual individuals remain to be designated.
A42: Consolidated records retain permanent IDs and links but are excluded from active counts. Consolidation does not mean resolution.
A43: Tolerable conclusions are conditional. Not tolerable requires treatment and management attention. Any temporary continuation needs appropriate authorization, interim safeguards and review.
A44: Awaiting assessment is an unresolved decision, not acceptance. Financial exposures must be considered together, including simultaneous claims, premium-income and investment pressure.

Sheet ReadMe
A2: Using the risk register
A5: Topic | B5: Instructions
A6: Scope | B6: This register records current risk identification, assessment, tolerability and existing controls. Detailed response implementation is maintained separately.
A7: Navigation | B7: Overview summarizes exposure. Record View displays one selected risk. RiskRegister contains editable records. Assessment Guide defines the criteria.
A8: Assessment date | B8: The initial assessment is as of April 1, 2020, with an event-likelihood horizon through June 30, 2020. Full consequences may extend beyond that period.
A9: References | B9: Record IDs are permanent. Risk Codes classify FIRM item, primary cause and sequence. Codes do not indicate severity. Never reuse retired IDs or codes.
A10: Consolidated records | B10: R-024 links to R-021, R-022 and R-025; R-027 to R-025; R-043 to R-037 and R-038. Retain these links and exclude consolidated entries from active totals.
A11: Ratings | B11: Likelihood and magnitude are inherent judgments before credit for controls. Use the categorical matrix, without multiplication. Related risks may arise from the same incident and must not be summed as independent losses.
A12: Tolerability | B12: Consider remaining exposure, controls, appetite, controllability and business necessity. Conditional tolerability remains subject to its stated assumptions. Awaiting assessment is not acceptance.
A13: Evidence | B13: Business outline(1).pdf provides the initial organizational facts; relevant page references remain in each record. Assessment assumptions and unverified controls are explicitly identified.
A14: Control effectiveness | B14: A supplier relationship, backup or written procedure does not itself demonstrate effectiveness. Proposed improvements must not be treated as operating controls.
A15: Ownership | B15: One accountable role is proposed for each active risk. Actual individuals and formal appointments remain to be confirmed.
A16: Editing | B16: Edit RiskRegister. Columns N and O contain likelihood and magnitude inputs; P calculates the matrix category. Overview and Record View are formula views.
... A21: Outstanding evidence | B21: Eleven financial assessments remain unresolved. Confirm exposures, cash forecasts, reserves, investment sensitivity and applicable reinsurance, including combined stress scenarios.
